connectpyse/__init__.py
connectpyse/config.py
connectpyse/cw_controller.py
connectpyse/cw_model.py
connectpyse/restapi.py
connectpyse/company/__init__.py
connectpyse/company/companies_api.py
connectpyse/company/company.py
connectpyse/company/company_management_summary_report.py
connectpyse/company/company_management_summary_reports_api.py
connectpyse/company/company_note.py
connectpyse/company/company_site.py
connectpyse/company/company_status.py
connectpyse/company/company_statuses_api.py
connectpyse/company/company_team.py
connectpyse/company/company_teams_api.py
connectpyse/company/company_type.py
connectpyse/company/company_types_api.py
connectpyse/company/configuration.py
connectpyse/company/configuration_status.py
connectpyse/company/configuration_type.py
connectpyse/company/configuration_type_question.py
connectpyse/company/configuration_types_api.py
connectpyse/company/configurations_api.py
connectpyse/company/contact.py
connectpyse/company/contact_communication.py
connectpyse/company/contact_communications_api.py
connectpyse/company/contact_department.py
connectpyse/company/contact_note.py
connectpyse/company/contact_relationship.py
connectpyse/company/contact_track.py
connectpyse/company/contact_type.py
connectpyse/company/contacts_api.py
connectpyse/expense/__init__.py
connectpyse/expense/expense_entry.py
connectpyse/expense/expense_type.py
connectpyse/finance/__init__.py
connectpyse/finance/accounting_batch.py
connectpyse/finance/accounting_batch_transaction.py
connectpyse/finance/accounting_unposted_expense.py
connectpyse/finance/accounting_unposted_invoice.py
connectpyse/finance/accounting_unposted_procurement.py
connectpyse/finance/agreement.py
connectpyse/finance/agreement_addition.py
connectpyse/finance/agreement_additions_api.py
connectpyse/finance/agreement_adjustment.py
connectpyse/finance/agreement_board_default.py
connectpyse/finance/agreement_site.py
connectpyse/finance/agreement_type.py
connectpyse/finance/agreement_work_role.py
connectpyse-0.8.1.dist-info/licenses/LICENSE
connectpyse-0.8.1.dist-info/METADATA
connectpyse-0.8.1.dist-info/WHEEL
connectpyse-0.8.1.dist-info/top_level.txt
connectpyse-0.8.1.dist-info/RECORD
