Metadata-Version: 2.4
Name: connectpyse
Version: 0.8.1
Summary: A ConnectWise API tool for the rest of us.
Author: @wesgann
Author-email: "Joshua M Smith (original)" <saether@gmail.com>, "Mark Ciecior (forked)" <mark@markciecior.com>
License: MIT
Project-URL: Homepage, https://github.com/markciecior/ConnectPyse
Keywords: connectwise,rest,api
Classifier: Development Status :: 3 - Alpha
Classifier: License :: OSI Approved :: MIT License
Classifier: Programming Language :: Python :: 3.5
Requires-Python: >=3.5
License-File: LICENSE
Requires-Dist: requests
Dynamic: license-file
